[
    {
        "name": "К-707Т БК",
        "id": "ID_MARK_BALTIETS_MODEL_K_707T_BK",
        "mark_id": "ID_MARK_BALTIETS"
    },
    {
        "name": "К-707Т-БКУ",
        "id": "ID_MARK_BALTIETS_MODEL_K_707T_BKU",
        "mark_id": "ID_MARK_BALTIETS"
    },
    {
        "name": "1150 (K-серия)",
        "id": "ID_MARK_CASE_MODEL_1150_K_SERIYA",
        "mark_id": "ID_MARK_CASE"
    },
    {
        "name": "1650 (K-серия)",
        "id": "ID_MARK_CASE_MODEL_1650_K_SERIYA",
        "mark_id": "ID_MARK_CASE"
    },
    {
        "name": "1650 (M-серия)",
        "id": "ID_MARK_CASE_MODEL_1650_M_SERIYA",
        "mark_id": "ID_MARK_CASE"
    },
    {
        "name": "2050 (M-серия)",
        "id": "ID_MARK_CASE_MODEL_2050_M_SERIYA",
        "mark_id": "ID_MARK_CASE"
    },
    {
        "name": "D10",
        "id": "ID_MARK_CATERPILLAR_MODEL_D10",
        "mark_id": "ID_MARK_CATERPILLAR"
    },
    {
        "name": "D11",
        "id": "ID_MARK_CATERPILLAR_MODEL_D11",
        "mark_id": "ID_MARK_CATERPILLAR"
    },
    {
        "name": "D3",
        "id": "ID_MARK_CATERPILLAR_MODEL_D3",
        "mark_id": "ID_MARK_CATERPILLAR"
    },
    {
        "name": "D4",
        "id": "ID_MARK_CATERPILLAR_MODEL_D4",
        "mark_id": "ID_MARK_CATERPILLAR"
    },
    {
        "name": "D5",
        "id": "ID_MARK_CATERPILLAR_MODEL_D5",
        "mark_id": "ID_MARK_CATERPILLAR"
    },
    {
        "name": "D6",
        "id": "ID_MARK_CATERPILLAR_MODEL_D6",
        "mark_id": "ID_MARK_CATERPILLAR"
    },
    {
        "name": "D7",
        "id": "ID_MARK_CATERPILLAR_MODEL_D7",
        "mark_id": "ID_MARK_CATERPILLAR"
    },
    {
        "name": "D8",
        "id": "ID_MARK_CATERPILLAR_MODEL_D8",
        "mark_id": "ID_MARK_CATERPILLAR"
    },
    {
        "name": "D9",
        "id": "ID_MARK_CATERPILLAR_MODEL_D9",
        "mark_id": "ID_MARK_CATERPILLAR"
    },
    {
        "name": "D6R2",
        "id": "ID_MARK_CATHEFENG_MODEL_D6R2",
        "mark_id": "ID_MARK_CATHEFENG"
    },
    {
        "name": "T20",
        "id": "ID_MARK_CHETRA_MODEL_T20",
        "mark_id": "ID_MARK_CHETRA"
    },
    {
        "name": "Т11",
        "id": "ID_MARK_CHETRA_MODEL_T11",
        "mark_id": "ID_MARK_CHETRA"
    },
    {
        "name": "Т15",
        "id": "ID_MARK_CHETRA_MODEL_T15",
        "mark_id": "ID_MARK_CHETRA"
    },
    {
        "name": "T25",
        "id": "ID_MARK_CHETRA_MODEL_T25",
        "mark_id": "ID_MARK_CHETRA"
    },
    {
        "name": "Т330",
        "id": "ID_MARK_CHETRA_MODEL_T330",
        "mark_id": "ID_MARK_CHETRA"
    },
    {
        "name": "Т9",
        "id": "ID_MARK_CHETRA_MODEL_T9",
        "mark_id": "ID_MARK_CHETRA"
    },
    {
        "name": "Т-35",
        "id": "ID_MARK_CHETRA_MODEL_T_35",
        "mark_id": "ID_MARK_CHETRA"
    },
    {
        "name": "Т-170",
        "id": "ID_MARK_CHTZ_MODEL_T_170",
        "mark_id": "ID_MARK_CHTZ"
    },
    {
        "name": "Б10.0001-1Е",
        "id": "ID_MARK_CHTZ_MODEL_B10_0001_1E",
        "mark_id": "ID_MARK_CHTZ"
    },
    {
        "name": "Б10.1111.ЕН",
        "id": "ID_MARK_CHTZ_MODEL_B10_1111_EN",
        "mark_id": "ID_MARK_CHTZ"
    },
    {
        "name": "Б12.6020-ЕН",
        "id": "ID_MARK_CHTZ_MODEL_B12_6020_EN",
        "mark_id": "ID_MARK_CHTZ"
    },
    {
        "name": "Б13",
        "id": "ID_MARK_CHTZ_MODEL_B13",
        "mark_id": "ID_MARK_CHTZ"
    },
    {
        "name": "Б-10М",
        "id": "ID_MARK_CHTZ_MODEL_B_10M",
        "mark_id": "ID_MARK_CHTZ"
    },
    {
        "name": "Б-10МБ",
        "id": "ID_MARK_CHTZ_MODEL_B_10MB",
        "mark_id": "ID_MARK_CHTZ"
    },
    {
        "name": "Б-11",
        "id": "ID_MARK_CHTZ_MODEL_B_11",
        "mark_id": "ID_MARK_CHTZ"
    },
    {
        "name": "Б-14",
        "id": "ID_MARK_CHTZ_MODEL_B_14",
        "mark_id": "ID_MARK_CHTZ"
    },
    {
        "name": "Б-170",
        "id": "ID_MARK_CHTZ_MODEL_B_170",
        "mark_id": "ID_MARK_CHTZ"
    },
    {
        "name": "ДЭТ-250",
        "id": "ID_MARK_CHTZ_MODEL_DET_250",
        "mark_id": "ID_MARK_CHTZ"
    },
    {
        "name": "ДЭТ-350",
        "id": "ID_MARK_CHTZ_MODEL_DET_350",
        "mark_id": "ID_MARK_CHTZ"
    },
    {
        "name": "ДЗ-171",
        "id": "ID_MARK_CHTZ_MODEL_DZ_171",
        "mark_id": "ID_MARK_CHTZ"
    },
    {
        "name": "Т-100",
        "id": "ID_MARK_CHTZ_MODEL_T_100",
        "mark_id": "ID_MARK_CHTZ"
    },
    {
        "name": "Т-130",
        "id": "ID_MARK_CHTZ_MODEL_T_130",
        "mark_id": "ID_MARK_CHTZ"
    },
    {
        "name": "Т-330",
        "id": "ID_MARK_CHTZ_MODEL_T_330",
        "mark_id": "ID_MARK_CHTZ"
    },
    {
        "name": "Б-10.V.М.0101-1E",
        "id": "ID_MARK_CHZT_MODEL_B_10_V_M_0101_1E",
        "mark_id": "ID_MARK_CHZT"
    },
    {
        "name": "B 100",
        "id": "ID_MARK_DORMASH_MODEL_B_100",
        "mark_id": "ID_MARK_DORMASH"
    },
    {
        "name": "TD",
        "id": "ID_MARK_DRESSTA_MODEL_TD",
        "mark_id": "ID_MARK_DRESSTA"
    },
    {
        "name": "ТМ10",
        "id": "ID_MARK_DST_URAL_MODEL_TM10",
        "mark_id": "ID_MARK_DST_URAL"
    },
    {
        "name": "ДЗ-110",
        "id": "ID_MARK_DZ_MODEL_DZ_110",
        "mark_id": "ID_MARK_DZ"
    },
    {
        "name": "ДЗ-109",
        "id": "ID_MARK_DZ_MODEL_DZ_109",
        "mark_id": "ID_MARK_DZ"
    },
    {
        "name": "ДЗ-143",
        "id": "ID_MARK_DZ_MODEL_DZ_143",
        "mark_id": "ID_MARK_DZ"
    },
    {
        "name": "FD",
        "id": "ID_MARK_FIAT_HITACHI_MODEL_FD",
        "mark_id": "ID_MARK_FIAT_HITACHI"
    },
    {
        "name": "CD5B",
        "id": "ID_MARK_FURUKAWA_MODEL_CD5B",
        "mark_id": "ID_MARK_FURUKAWA"
    },
    {
        "name": "TY165-2",
        "id": "ID_MARK_HBXG_MODEL_TY165_2",
        "mark_id": "ID_MARK_HBXG"
    },
    {
        "name": "T165-2",
        "id": "ID_MARK_HBXG_MODEL_T165_2",
        "mark_id": "ID_MARK_HBXG"
    },
    {
        "name": "DX45",
        "id": "ID_MARK_HITACHI_MODEL_DX45",
        "mark_id": "ID_MARK_HITACHI"
    },
    {
        "name": "1050J",
        "id": "ID_MARK_JOHN_DEERE_MODEL_1050J",
        "mark_id": "ID_MARK_JOHN_DEERE"
    },
    {
        "name": "1050K",
        "id": "ID_MARK_JOHN_DEERE_MODEL_1050K",
        "mark_id": "ID_MARK_JOHN_DEERE"
    },
    {
        "name": "700J",
        "id": "ID_MARK_JOHN_DEERE_MODEL_700J",
        "mark_id": "ID_MARK_JOHN_DEERE"
    },
    {
        "name": "750J",
        "id": "ID_MARK_JOHN_DEERE_MODEL_750J",
        "mark_id": "ID_MARK_JOHN_DEERE"
    },
    {
        "name": "850J",
        "id": "ID_MARK_JOHN_DEERE_MODEL_850J",
        "mark_id": "ID_MARK_JOHN_DEERE"
    },
    {
        "name": "850J2",
        "id": "ID_MARK_JOHN_DEERE_MODEL_850J2",
        "mark_id": "ID_MARK_JOHN_DEERE"
    },
    {
        "name": "К-702",
        "id": "ID_MARK_KIROVETS_MODEL_K_702_BULLDOZER",
        "mark_id": "ID_MARK_KIROVETS"
    },
    {
        "name": "К-703",
        "id": "ID_MARK_KIROVETS_MODEL_K_703_BULLDOZER",
        "mark_id": "ID_MARK_KIROVETS"
    },
    {
        "name": "PengPu",
        "id": "ID_MARK_KIROVETS_MODEL_PENGPU",
        "mark_id": "ID_MARK_KIROVETS"
    },
    {
        "name": "D105",
        "id": "ID_MARK_KOMATSU_MODEL_D105",
        "mark_id": "ID_MARK_KOMATSU"
    },
    {
        "name": "D155",
        "id": "ID_MARK_KOMATSU_MODEL_D155",
        "mark_id": "ID_MARK_KOMATSU"
    },
    {
        "name": "D20",
        "id": "ID_MARK_KOMATSU_MODEL_D20",
        "mark_id": "ID_MARK_KOMATSU"
    },
    {
        "name": "D275",
        "id": "ID_MARK_KOMATSU_MODEL_D275",
        "mark_id": "ID_MARK_KOMATSU"
    },
    {
        "name": "D31S",
        "id": "ID_MARK_KOMATSU_MODEL_D31S",
        "mark_id": "ID_MARK_KOMATSU"
    },
    {
        "name": "D355",
        "id": "ID_MARK_KOMATSU_MODEL_D355",
        "mark_id": "ID_MARK_KOMATSU"
    },
    {
        "name": "D37",
        "id": "ID_MARK_KOMATSU_MODEL_D37",
        "mark_id": "ID_MARK_KOMATSU"
    },
    {
        "name": "D375",
        "id": "ID_MARK_KOMATSU_MODEL_D375",
        "mark_id": "ID_MARK_KOMATSU"
    },
    {
        "name": "D39",
        "id": "ID_MARK_KOMATSU_MODEL_D39",
        "mark_id": "ID_MARK_KOMATSU"
    },
    {
        "name": "D41",
        "id": "ID_MARK_KOMATSU_MODEL_D41",
        "mark_id": "ID_MARK_KOMATSU"
    },
    {
        "name": "D475",
        "id": "ID_MARK_KOMATSU_MODEL_D475",
        "mark_id": "ID_MARK_KOMATSU"
    },
    {
        "name": "D50",
        "id": "ID_MARK_KOMATSU_MODEL_D50",
        "mark_id": "ID_MARK_KOMATSU"
    },
    {
        "name": "D51",
        "id": "ID_MARK_KOMATSU_MODEL_D51",
        "mark_id": "ID_MARK_KOMATSU"
    },
    {
        "name": "D53",
        "id": "ID_MARK_KOMATSU_MODEL_D53",
        "mark_id": "ID_MARK_KOMATSU"
    },
    {
        "name": "D61",
        "id": "ID_MARK_KOMATSU_MODEL_D61",
        "mark_id": "ID_MARK_KOMATSU"
    },
    {
        "name": "D63",
        "id": "ID_MARK_KOMATSU_MODEL_D63",
        "mark_id": "ID_MARK_KOMATSU"
    },
    {
        "name": "D65",
        "id": "ID_MARK_KOMATSU_MODEL_D65",
        "mark_id": "ID_MARK_KOMATSU"
    },
    {
        "name": "D85",
        "id": "ID_MARK_KOMATSU_MODEL_D85",
        "mark_id": "ID_MARK_KOMATSU"
    },
    {
        "name": "Т-70",
        "id": "ID_MARK_KTZ_TRAKOM_MODEL_T_70_BULLDOZER",
        "mark_id": "ID_MARK_KTZ_TRAKOM"
    },
    {
        "name": "PR 714",
        "id": "ID_MARK_LIEBHERR_MODEL_PR_714",
        "mark_id": "ID_MARK_LIEBHERR"
    },
    {
        "name": "PR 722",
        "id": "ID_MARK_LIEBHERR_MODEL_PR_722",
        "mark_id": "ID_MARK_LIEBHERR"
    },
    {
        "name": "PR 724",
        "id": "ID_MARK_LIEBHERR_MODEL_PR_724",
        "mark_id": "ID_MARK_LIEBHERR"
    },
    {
        "name": "PR 732",
        "id": "ID_MARK_LIEBHERR_MODEL_PR_732",
        "mark_id": "ID_MARK_LIEBHERR"
    },
    {
        "name": "PR 734 L Litronic",
        "id": "ID_MARK_LIEBHERR_MODEL_PR_734_L_LITRONIC",
        "mark_id": "ID_MARK_LIEBHERR"
    },
    {
        "name": "PR 742",
        "id": "ID_MARK_LIEBHERR_MODEL_PR_742",
        "mark_id": "ID_MARK_LIEBHERR"
    },
    {
        "name": "PR 744",
        "id": "ID_MARK_LIEBHERR_MODEL_PR_744",
        "mark_id": "ID_MARK_LIEBHERR"
    },
    {
        "name": "PR 752 Litronic",
        "id": "ID_MARK_LIEBHERR_MODEL_PR_752_LITRONIC",
        "mark_id": "ID_MARK_LIEBHERR"
    },
    {
        "name": "PR 764 Litronic",
        "id": "ID_MARK_LIEBHERR_MODEL_PR_764_LITRONIC",
        "mark_id": "ID_MARK_LIEBHERR"
    },
    {
        "name": "CLGB 160",
        "id": "ID_MARK_LIUGONG_MODEL_CLGB_160",
        "mark_id": "ID_MARK_LIUGONG"
    },
    {
        "name": "CLGB 230",
        "id": "ID_MARK_LIUGONG_MODEL_CLGB_230",
        "mark_id": "ID_MARK_LIUGONG"
    },
    {
        "name": "CLGB 320",
        "id": "ID_MARK_LIUGONG_MODEL_CLGB_320",
        "mark_id": "ID_MARK_LIUGONG"
    },
    {
        "name": "MF3366",
        "id": "ID_MARK_MASSEY_FERGUSON_MODEL_MF3366",
        "mark_id": "ID_MARK_MASSEY_FERGUSON"
    },
    {
        "name": "BD2G",
        "id": "ID_MARK_MITSUBISHI_MODEL_BD2G",
        "mark_id": "ID_MARK_MITSUBISHI"
    },
    {
        "name": "ДТ-75",
        "id": "ID_MARK_MTZ_MODEL_DT_75",
        "mark_id": "ID_MARK_MTZ"
    },
    {
        "name": "МТЗ",
        "id": "ID_MARK_MTZ_MODEL_MTZ",
        "mark_id": "ID_MARK_MTZ"
    },
    {
        "name": "D 180",
        "id": "ID_MARK_NEW_HOLLAND_MODEL_D_180",
        "mark_id": "ID_MARK_NEW_HOLLAND"
    },
    {
        "name": "D 255",
        "id": "ID_MARK_NEW_HOLLAND_MODEL_D_255",
        "mark_id": "ID_MARK_NEW_HOLLAND"
    },
    {
        "name": "D 350",
        "id": "ID_MARK_NEW_HOLLAND_MODEL_D_350",
        "mark_id": "ID_MARK_NEW_HOLLAND"
    },
    {
        "name": "Трелевочные трактора",
        "id": "ID_MARK_OTZ_MODEL_TRELEVOCHNYE_TRAKTORA",
        "mark_id": "ID_MARK_OTZ"
    },
    {
        "name": "PD",
        "id": "ID_MARK_PENGPU_MODEL_PD",
        "mark_id": "ID_MARK_PENGPU"
    },
    {
        "name": "Бульдозеры",
        "id": "ID_MARK_PROMTRAKTOR_CHZPT_MODEL_BULDOZERY",
        "mark_id": "ID_MARK_PROMTRAKTOR_CHZPT"
    },
    {
        "name": "ПКТ-2",
        "id": "ID_MARK_RUSICH_KZKT_MODEL_PKT_2",
        "mark_id": "ID_MARK_RUSICH_KZKT"
    },
    {
        "name": "816",
        "id": "ID_MARK_SEM_MODEL_816",
        "mark_id": "ID_MARK_SEM"
    },
    {
        "name": "822",
        "id": "ID_MARK_SEM_MODEL_822",
        "mark_id": "ID_MARK_SEM"
    },
    {
        "name": "SD",
        "id": "ID_MARK_SHANTUI_MODEL_SD",
        "mark_id": "ID_MARK_SHANTUI"
    },
    {
        "name": "T",
        "id": "ID_MARK_SHANTUI_MODEL_T",
        "mark_id": "ID_MARK_SHANTUI"
    },
    {
        "name": "TY 165-2",
        "id": "ID_MARK_SHEHWA_MODEL_TY_165_2",
        "mark_id": "ID_MARK_SHEHWA"
    },
    {
        "name": "SD 7",
        "id": "ID_MARK_SHEHWA_MODEL_SD_7",
        "mark_id": "ID_MARK_SHEHWA"
    },
    {
        "name": "SD 7HW",
        "id": "ID_MARK_SHEHWA_MODEL_SD_7HW",
        "mark_id": "ID_MARK_SHEHWA"
    },
    {
        "name": "SD 7LGP",
        "id": "ID_MARK_SHEHWA_MODEL_SD_7LGP",
        "mark_id": "ID_MARK_SHEHWA"
    },
    {
        "name": "SD 8B",
        "id": "ID_MARK_SHEHWA_MODEL_SD_8B",
        "mark_id": "ID_MARK_SHEHWA"
    },
    {
        "name": "SD 9",
        "id": "ID_MARK_SHEHWA_MODEL_SD_9",
        "mark_id": "ID_MARK_SHEHWA"
    },
    {
        "name": "TS 165-2",
        "id": "ID_MARK_SHEHWA_MODEL_TS_165_2",
        "mark_id": "ID_MARK_SHEHWA"
    },
    {
        "name": "TS 165-2HW",
        "id": "ID_MARK_SHEHWA_MODEL_TS_165_2HW",
        "mark_id": "ID_MARK_SHEHWA"
    },
    {
        "name": "TYS 165-2",
        "id": "ID_MARK_SHEHWA_MODEL_TYS_165_2",
        "mark_id": "ID_MARK_SHEHWA"
    },
    {
        "name": "TYS 165-2HW",
        "id": "ID_MARK_SHEHWA_MODEL_TYS_165_2HW",
        "mark_id": "ID_MARK_SHEHWA"
    },
    {
        "name": "TYS 165-3",
        "id": "ID_MARK_SHEHWA_MODEL_TYS_165_3",
        "mark_id": "ID_MARK_SHEHWA"
    },
    {
        "name": "TY 165-3",
        "id": "ID_MARK_SHEHWA_MODEL_TY_165_3",
        "mark_id": "ID_MARK_SHEHWA"
    },
    {
        "name": "T 165-2",
        "id": "ID_MARK_SHEHWA_MODEL_T_165_2",
        "mark_id": "ID_MARK_SHEHWA"
    },
    {
        "name": "Бульдозеры",
        "id": "ID_MARK_SPETSSTROYMASH_MODEL_BULDOZERY",
        "mark_id": "ID_MARK_SPETSSTROYMASH"
    },
    {
        "name": "ДТ-75/ДЗ-42",
        "id": "ID_MARK_VGTZ_MODEL_DT_75_DZ_42",
        "mark_id": "ID_MARK_VGTZ"
    },
    {
        "name": "TY 160",
        "id": "ID_MARK_XCMG_MODEL_TY_160",
        "mark_id": "ID_MARK_XCMG"
    },
    {
        "name": "TY 230",
        "id": "ID_MARK_XCMG_MODEL_TY_230",
        "mark_id": "ID_MARK_XCMG"
    },
    {
        "name": "TY320",
        "id": "ID_MARK_XGMA_MODEL_TY320",
        "mark_id": "ID_MARK_XGMA"
    },
    {
        "name": "XG4161",
        "id": "ID_MARK_XGMA_MODEL_XG4161",
        "mark_id": "ID_MARK_XGMA"
    },
    {
        "name": "XG",
        "id": "ID_MARK_XIAGONG_MODEL_XG",
        "mark_id": "ID_MARK_XIAGONG"
    },
    {
        "name": "ZD",
        "id": "ID_MARK_ZOOMLION_MODEL_ZD",
        "mark_id": "ID_MARK_ZOOMLION"
    },
    {
        "name": "ZD160-3",
        "id": "ID_MARK_ZOOMLION_MODEL_ZD160_3",
        "mark_id": "ID_MARK_ZOOMLION"
    },
    {
        "name": "ZD220-3",
        "id": "ID_MARK_ZOOMLION_MODEL_ZD220_3",
        "mark_id": "ID_MARK_ZOOMLION"
    },
    {
        "name": "ZD320-3",
        "id": "ID_MARK_ZOOMLION_MODEL_ZD320_3",
        "mark_id": "ID_MARK_ZOOMLION"
    }
]